Juwel/Date_formatter.py
Juwel/GUI_element_finder.py
Juwel/Json_transf.py
Juwel/Main.py
Juwel/Prolongation_finder.py
Juwel/Text_parser.py
Juwel/__init__.py
Juwel-2.1.2.dist-info/METADATA
Juwel-2.1.2.dist-info/WHEEL
Juwel-2.1.2.dist-info/entry_points.txt
Juwel-2.1.2.dist-info/top_level.txt
Juwel-2.1.2.dist-info/RECORD
