Metadata-Version: 2.1
Name: Juwel
Version: 2.1.2
Summary: Sidecar file generator
Home-page: UNKNOWN
Author: Gefan Qian
Author-email: qian@cbs.mpg.de
License: GPL
Platform: UNKNOWN
Requires-Python: >=3.6
Requires-Dist: tk
Requires-Dist: tkcalendar
